pygieons/__init__.py
pygieons/ecosystem_connections.py
pygieons/ecosystem_pkgs.py
pygieons/pygieons.py
pygieons-0.0.1.dist-info/LICENSE
pygieons-0.0.1.dist-info/METADATA
pygieons-0.0.1.dist-info/WHEEL
pygieons-0.0.1.dist-info/top_level.txt
pygieons-0.0.1.dist-info/RECORD
